setup.py
demopkgkrishnatest/__init__.py
demopkgkrishnatest/calculator.py
demopkgkrishnatest.egg-info/PKG-INFO
demopkgkrishnatest.egg-info/SOURCES.txt
demopkgkrishnatest.egg-info/dependency_links.txt
demopkgkrishnatest.egg-info/top_level.txt