Metadata-Version: 2.1
Name: demopkgkrishnatest
Version: 0.0.1
Summary: kr python module
Home-page: UNKNOWN
Author: bhanushali-adi
Author-email: krishna.bhanushali@analog.com
License: UNKNOWN
Platform: UNKNOWN
Classifier: Programming Language :: Python :: 3
Classifier: Operating System :: OS Independent
